lbcs/README.md
lbcs/__init__.py
lbcs/config.py
lbcs/example_config.ini
lbcs/gridWebSocket.js
lbcs/index.html
lbcs/lbcs.service
lbcs/server.py
lbcs/splash.png
lbcs/test_handlers.py
lbcs-0.13.0.dist-info/entry_points.txt
lbcs-0.13.0.dist-info/WHEEL
lbcs-0.13.0.dist-info/METADATA
lbcs-0.13.0.dist-info/RECORD
